qt_logging/__init__.py
qt_logging/button.py
qt_logging/logger.py
qt_logging-0.1.0.dist-info/LICENSE
qt_logging-0.1.0.dist-info/METADATA
qt_logging-0.1.0.dist-info/WHEEL
qt_logging-0.1.0.dist-info/top_level.txt
qt_logging-0.1.0.dist-info/RECORD
