Metadata-Version: 2.2
Name: qt-logging
Version: 0.1.0
Summary: Log viewer and status bar for Qt applications
Author: Beat Reichenbach
License: MIT
Requires-Python: >=3.9
License-File: LICENSE
Requires-Dist: qtpy<3,>=2.0
Requires-Dist: qt-material-icons<1,>=0.2
Provides-Extra: dev
Requires-Dist: black>=24.0; extra == "dev"
Requires-Dist: python-semantic-release>=9.0; extra == "dev"
Requires-Dist: qt-themes>=0.2; extra == "dev"
Requires-Dist: PySide6; extra == "dev"
Provides-Extra: pyside2
Requires-Dist: PySide2; extra == "pyside2"
Provides-Extra: pyside6
Requires-Dist: PySide6; extra == "pyside6"
